nrql_api/__init__.py
nrql_api/request.py
nrql_api/response.py
nrql_api-0.0.10.dist-info/METADATA
nrql_api-0.0.10.dist-info/WHEEL
nrql_api-0.0.10.dist-info/top_level.txt
nrql_api-0.0.10.dist-info/RECORD
